{
    "14. Главная страница": {
        "type": "active",
        "url": "https://garmonia-stacionar.ru/netcat/admin/#object.list(14)"
    },
    "13. Поиск": {
        "type": "unactive",
        "url": "https://garmonia-stacionar.ru/netcat/admin/#object.list(10)"
    },
    "37. О клинике": {
        "type": "active",
        "url": "https://garmonia-stacionar.ru/netcat/admin/#object.list(35)"
    },
    "52. Новости": {
        "type": "active",
        "url": "https://garmonia-stacionar.ru/netcat/admin/#object.list(50)"
    },
    "49. Наши документы и лицензии": {
        "type": "active",
        "url": "https://garmonia-stacionar.ru/netcat/admin/#object.list(47)"
    },
    "84. Фотогалерея": {
        "type": "active",
        "url": "https://garmonia-stacionar.ru/netcat/admin/#object.list(84)"
    },
    "39. Отзывы": {
        "type": "active",
        "url": "https://garmonia-stacionar.ru/netcat/admin/#object.list(37)"
    },
    "21. Врачи": {
        "type": "active",
        "url": "https://garmonia-stacionar.ru/netcat/admin/#object.list(19)"
    },
    "20. Услуги": {
        "type": "active",
        "url": "https://garmonia-stacionar.ru/netcat/admin/#object.list(18)"
    },
    "88. Цены": {
        "type": "active",
        "url": "https://garmonia-stacionar.ru/netcat/admin/#object.list(92)"
    },
    "19. Курсы лечения": {
        "type": "active",
        "url": "https://garmonia-stacionar.ru/netcat/admin/#object.list(90)"
    },
    "35. Страница статьи": {
        "type": "unactive",
        "url": "https://garmonia-stacionar.ru/netcat/admin/#object.list(103)"
    },
    "18. Контакты": {
        "type": "active",
        "url": "https://garmonia-stacionar.ru/netcat/admin/#object.list(16)"
    },
    "24. Заявка": {
        "type": "unactive",
        "url": "https://garmonia-stacionar.ru/netcat/admin/#object.list(22)"
    },
    "38. Полезная информация": {
        "type": "unactive",
        "url": "https://garmonia-stacionar.ru/netcat/admin/#object.list(36)"
    },
    "53. Контролирующие органы": {
        "type": "unactive",
        "url": "https://garmonia-stacionar.ru/netcat/admin/#object.list(51)"
    },
    "82. Информирование граждан": {
        "type": "unactive",
        "url": "https://garmonia-stacionar.ru/netcat/admin/#object.list(81)"
    },
    "68. Реквизиты": {
        "type": "unactive",
        "url": "https://garmonia-stacionar.ru/netcat/admin/#object.list(66)"
    },
    "16. Соглашение об использовании сайта": {
        "type": "unactive",
        "url": "https://garmonia-stacionar.ru/netcat/admin/#subdivision.design(16)"
    },
    "69. Политика конфиденциальности": {
        "type": "unactive",
        "url": "https://garmonia-stacionar.ru/netcat/admin/#object.list(67)"
    },
    "15. Страница не найдена (ошибка 404)": {
        "type": "unactive",
        "url": "https://garmonia-stacionar.ru/netcat/admin/#subdivision.design(15)"
    },
    "87. Карта сайта": {
        "type": "active",
        "url": "https://garmonia-stacionar.ru/netcat/admin/#object.list(91)"
    },
    "85. Оставить отзыв": {
        "type": "unactive",
        "url": "https://garmonia-stacionar.ru/netcat/admin/#object.list(85)"
    },
    "107. Приватные отзывы": {
        "type": "unactive",
        "url": "https://garmonia-stacionar.ru/netcat/admin/#object.list(114)"
    },
    "108. Поиск по сайту": {
        "type": "active",
        "url": "https://garmonia-stacionar.ru/netcat/admin/#object.list(115)"
    },
    "126. Лендинг-терапия": {
        "type": "unactive",
        "url": "https://garmonia-stacionar.ru/netcat/admin/#object.list(131)"
    },
    "128. Лендинг-наркология": {
        "type": "unactive",
        "url": "https://garmonia-stacionar.ru/netcat/admin/#object.list(137)"
    },
    "130. Отзывы наркология": {
        "type": "unactive",
        "url": "https://garmonia-stacionar.ru/netcat/admin/#object.list(135)"
    }
}